r34/Constants.py
r34/Errors.py
r34/Gateway.py
r34/Media.py
r34/Site.py
r34/Types.py
r34/__init__.py
r34-0.0.1.dist-info/METADATA
r34-0.0.1.dist-info/WHEEL
r34-0.0.1.dist-info/top_level.txt
r34-0.0.1.dist-info/RECORD
