Metadata-Version: 2.1
Name: r34
Version: 0.0.1
Summary: Library for retrieving posts and tags from rule34.us
Home-page: https://github.com/ArticOff/r34
Author: Artic#3065
Author-email: artic.admisoffi@gmail.com
Maintainer: Artic#3065
Maintainer-email: artic.admisoffi@gmail.com
License: MIT
Project-URL: Source, https://github.com/ArticOff/r34
Project-URL: Discord, https://articoff.github.io/discord
Project-URL: Tracker, https://github.com/ArticOff/r34/issues
Platform: UNKNOWN
Classifier: License :: OSI Approved :: MIT License
Classifier: Intended Audience :: Developers
Classifier: Intended Audience :: Customer Service
Classifier: Natural Language :: English
Classifier: Programming Language :: Python :: 3
Classifier: Programming Language :: Python
Classifier: Environment :: Console
Classifier: Environment :: Win32 (MS Windows)
Classifier: Framework :: Pytest
Classifier: Operating System :: OS Independent
Requires-Dist: innerhtml
Requires-Dist: requests
